django_fsm_freeze/__init__.py
django_fsm_freeze/exceptions.py
django_fsm_freeze/models.py
django_fsm_freeze-0.1.9.dist-info/LICENSE
django_fsm_freeze-0.1.9.dist-info/WHEEL
django_fsm_freeze-0.1.9.dist-info/METADATA
django_fsm_freeze-0.1.9.dist-info/RECORD
