Metadata-Version: 2.1
Name: django-fsm-freeze
Version: 0.1.9
Summary: django-fsm data immutability support
Home-page: https://github.com/ming-tung/django-fsm-freeze
License: MIT
Author: ming-tung
Author-email: mingtung.hong@gmail.com
Requires-Python: >=3.9,<4.0
Classifier: License :: OSI Approved :: MIT License
Classifier: Programming Language :: Python :: 3
Classifier: Programming Language :: Python :: 3.9
Requires-Dist: Django
Requires-Dist: django-dirtyfields (>=1.7.0,<2.0.0)
Requires-Dist: django-fsm
Project-URL: Repository, https://github.com/ming-tung/django-fsm-freeze
